arrdem.datalog-0.0.1.data/scripts/datalog
datalog/__init__.py
datalog/core.py
datalog/parser.py
arrdem.datalog-0.0.1.dist-info/LICENSE.md
arrdem.datalog-0.0.1.dist-info/METADATA
arrdem.datalog-0.0.1.dist-info/WHEEL
arrdem.datalog-0.0.1.dist-info/top_level.txt
arrdem.datalog-0.0.1.dist-info/RECORD
