Metadata-Version: 1.1
Name: arrdem.datalog
Version: 0.0.1
Summary: A Datalog engine
Home-page: https://git.arrdem.com/arrdem/datalog-py
Author: Reid 'arrdem' McKenzie
Author-email: me@arrdem.com
License: MIT
Platform: UNKNOWN
Classifier: Development Status :: 3 - Alpha
Classifier: Intended Audience :: Developers
Classifier: License :: OSI Approved :: MIT License
Classifier: Programming Language :: Python :: 3
Classifier: Programming Language :: Python :: 3.6
Classifier: Programming Language :: Python :: 3.7
